asyncmost_vasiaplaton/__init__.py
asyncmost_vasiaplaton/exceptions.py
asyncmost_vasiaplaton/mattermost.py
asyncmost_vasiaplaton-0.1.2.dist-info/LICENSE
asyncmost_vasiaplaton-0.1.2.dist-info/METADATA
asyncmost_vasiaplaton-0.1.2.dist-info/WHEEL
asyncmost_vasiaplaton-0.1.2.dist-info/top_level.txt
asyncmost_vasiaplaton-0.1.2.dist-info/RECORD
