Metadata-Version: 2.1
Name: asyncmost_vasiaplaton
Version: 0.1.2
Summary: A Python package to async interact with Mattermost API
Author-email: Vasilii Platon <vasia.platon@gmail.com>
Project-URL: Homepage, https://github.com/vasiaplaton/asyncmost
Project-URL: Issues, https://github.com/vasiaplaton/asyncmost/issues
Classifier: Programming Language :: Python :: 3
Classifier: License :: OSI Approved :: MIT License
Classifier: Operating System :: OS Independent
Requires-Python: >=3.8
License-File: LICENSE
Requires-Dist: httpx<1.0.0,>=0.20.0
